wsdot/__init__.py
wsdot-0.0.0.dist-info/METADATA
wsdot-0.0.0.dist-info/WHEEL
wsdot-0.0.0.dist-info/licenses/LICENSE
wsdot-0.0.0.dist-info/RECORD
