Metadata-Version: 2.4
Name: wsdot
Version: 0.0.0
Summary: A Python wrapper of the wsdot.wa.gov APIs
Project-URL: Home, https://github.com/ucodery/wsdot
Author-email: Jeremiah Paige <ucodery@gmail.com>
License-Expression: BSD-3-Clause
License-File: LICENSE
Requires-Dist: aiohttp
Requires-Dist: pydantic
